clean_folder_by_MK/___init___.py
clean_folder_by_MK/main.py
clean_folder_by_MK/tools.py
clean_folder_by_MK-1.0.0.dist-info/LICENSE
clean_folder_by_MK-1.0.0.dist-info/METADATA
clean_folder_by_MK-1.0.0.dist-info/WHEEL
clean_folder_by_MK-1.0.0.dist-info/top_level.txt
clean_folder_by_MK-1.0.0.dist-info/RECORD
