Metadata-Version: 2.1
Name: clean_folder_by_MK
Version: 1.0.0
Summary: Script for sorting files in junked folders
Author-email: Maksym Klym <maxymklym1996@gmail.com>
License: Copyright (c) 2023 Maksym Klym
Project-URL: Homepage, https://github.com/takeRednotBlue/Python-core/tree/main-chgd/hw7/HW_project/clean_folder_by_MK
Classifier: Programming Language :: Python :: 3
Classifier: License :: OSI Approved :: MIT License
Classifier: Operating System :: OS Independent
Requires-Python: >=3.9
License-File: LICENSE
